binary_file_parser/__init__.py
binary_file_parser/logger.py
binary_file_parser/utils.py
binary_file_parser/errors/__init__.py
binary_file_parser/errors/compression_error.py
binary_file_parser/errors/default_value_error.py
binary_file_parser/errors/parsing_error.py
binary_file_parser/errors/version_error.py
binary_file_parser/retrievers/__init__.py
binary_file_parser/retrievers/map_validate.py
binary_file_parser/retrievers/retriever.py
binary_file_parser/retrievers/retriever_combiner.py
binary_file_parser/retrievers/retriever_ref.py
binary_file_parser/retrievers/type_cast.py
binary_file_parser/types/__init__.py
binary_file_parser/types/base_struct.py
binary_file_parser/types/byte_stream.py
binary_file_parser/types/debug_byte_stream.py
binary_file_parser/types/manager.py
binary_file_parser/types/parseable.py
binary_file_parser/types/version.py
binary_file_parser/types/le/__init__.py
binary_file_parser/types/le/array.py
binary_file_parser/types/le/bool.py
binary_file_parser/types/le/bytes.py
binary_file_parser/types/le/float.py
binary_file_parser/types/le/int.py
binary_file_parser/types/le/option.py
binary_file_parser/types/le/string.py
binary_file_parser-0.2.2.dist-info/LICENSE
binary_file_parser-0.2.2.dist-info/METADATA
binary_file_parser-0.2.2.dist-info/WHEEL
binary_file_parser-0.2.2.dist-info/top_level.txt
binary_file_parser-0.2.2.dist-info/RECORD
