Metadata-Version: 2.1
Name: binary-file-parser
Version: 0.2.2
Summary: Read/Write binary files after describing their specifications in code (similar to an ORM table schema)
Author-email: Divy1211 <divy1211.dc@gmail.com>
License: GNU GENERAL PUBLIC LICENSE
Project-URL: Homepage, https://github.com/Divy1211/BinaryFileParser
Keywords: binary,file,parser
Classifier: License :: OSI Approved :: MIT License
Classifier: Programming Language :: Python
Classifier: Programming Language :: Python :: 3
Classifier: Operating System :: OS Independent
Requires-Python: >=3.10
License-File: LICENSE
Requires-Dist: alive-progress
Provides-Extra: depl
Requires-Dist: build; extra == "depl"
Requires-Dist: twine; extra == "depl"
Provides-Extra: dev
Requires-Dist: pytest; extra == "dev"
Requires-Dist: pylint; extra == "dev"
Requires-Dist: mypy; extra == "dev"
Requires-Dist: flake8; extra == "dev"
Provides-Extra: docs
Requires-Dist: mkdocs; extra == "docs"
Requires-Dist: mkdocstrings; extra == "docs"
